pymongoext/__init__.py
pymongoext/binder.py
pymongoext/binder.pyi
pymongoext/cursor.py
pymongoext/document.py
pymongoext/exceptions.py
pymongoext/fields.py
pymongoext/manipulators.py
pymongoext/model.py
pymongoext-2.3.3.dist-info/LICENSE
pymongoext-2.3.3.dist-info/METADATA
pymongoext-2.3.3.dist-info/WHEEL
pymongoext-2.3.3.dist-info/top_level.txt
pymongoext-2.3.3.dist-info/RECORD
