Metadata-Version: 2.1
Name: pymongoext
Version: 2.3.3
Summary: An ORM-like Pymongo extension that adds json schema validation, index management and intermediate data manipulators
Home-page: https://github.com/musyoka-morris/pymongoext
Author: Musyoka Morris
Author-email: musyokamorris@gmail.com
License: MIT
Keywords: mongo mongodb database pymongo validation jsonschema schema indexes orm
Platform: UNKNOWN
Classifier: Development Status :: 3 - Alpha
Classifier: Intended Audience :: Developers
Classifier: Programming Language :: Python :: 3
Classifier: Programming Language :: Python :: 3.5
Classifier: Programming Language :: Python :: 3.6
Classifier: Programming Language :: Python :: 3.7
Requires-Python: >=3
Requires-Dist: inflection
Requires-Dist: pymongo
Requires-Dist: python-dateutil
Requires-Dist: munch
Requires-Dist: fastnumbers
